offlinesec_connector/__init__.py
offlinesec_connector/conn_func.py
offlinesec_connector/conn_secnotes.py
offlinesec_connector/key_storage.py
offlinesec_connector/mng_offlinesec_conn.py
offlinesec_connector/offlinesec_connector.py
offlinesec_connector/offlinesec_files.py
offlinesec_connector/rfc_conn_list.py
offlinesec_connector/rfc_connection.py
offlinesec_connector-0.0.12.dist-info/METADATA
offlinesec_connector-0.0.12.dist-info/WHEEL
offlinesec_connector-0.0.12.dist-info/entry_points.txt
offlinesec_connector-0.0.12.dist-info/top_level.txt
offlinesec_connector-0.0.12.dist-info/RECORD
