Metadata-Version: 2.1
Name: offlinesec-connector
Version: 0.0.12
Summary: Offline Security Connector
Home-page: https://offlinesec.com
Author: Offline Security
Author-email: info@offlinesec.com
License: UNKNOWN
Platform: UNKNOWN
Requires-Dist: PyYAML (~=6.0.1)
Requires-Dist: pyrfc (==3.3.1)
Requires-Dist: keyring (~=25.6.0)
Requires-Dist: setuptools (~=57.0.0)
